xmlstarlet-1.6.8.dist-info/AUTHORS.rst
xmlstarlet-1.6.8.dist-info/WHEEL
xmlstarlet-1.6.8.dist-info/top_level.txt
xmlstarlet-1.6.8.dist-info/METADATA
xmlstarlet-1.6.8.dist-info/RECORD
xmlstarlet-1.6.8.dist-info/LICENSE
xmlstarlet.libs/libgpg-error-3222c8df.so.0.10.0
xmlstarlet.libs/libgcrypt-d95bd281.so.11.8.2
xmlstarlet.libs/libxml2-4b32ec39.so.2.9.1
xmlstarlet.libs/libexslt-e92dcb43.so.0.8.17
xmlstarlet.libs/liblzma-ee60765a.so.5.2.2
xmlstarlet.libs/libxslt-a81ffc89.so.1.1.28
xmlstarlet/_xmlstarlet.abi3.so
xmlstarlet/__init__.py
