Metadata-Version: 2.1
Name: xmlstarlet
Version: 1.6.8
Summary: XMLStarlet Toolkit: Python CFFI bindings
Home-page: https://github.com/dimitern/xmlstarlet
Author: Mikhail Grushinskiy
Author-email: mgrouch@users.sourceforge.net
Maintainer: Dimiter Naydenov
Maintainer-email: dimitern@users.noreply.github.com
License: MIT license
Keywords: xmlstarlet cffi
Platform: UNKNOWN
Classifier: Development Status :: 6 - Mature
Classifier: Intended Audience :: Developers
Classifier: License :: OSI Approved :: MIT License
Classifier: Natural Language :: English
Classifier: Programming Language :: Python :: 3
Classifier: Programming Language :: Python :: 3.4
Classifier: Programming Language :: Python :: 3.5
Classifier: Programming Language :: Python :: 3.6
Classifier: Programming Language :: Python :: 3.7
Classifier: Programming Language :: Python :: 3.8
Classifier: Programming Language :: Python :: 3.9
Classifier: Programming Language :: Python :: 3.10
Requires-Python: >=3.6.*
License-File: LICENSE
License-File: AUTHORS.rst
